Metadata-Version: 2.1
Name: convertpngs
Version: 0.0.3
Summary: a module about converting pngs to gif or video in simplified ways.
Home-page: 
Author: CYC
Author-email: vichouro@gmail.com
License: MIT
Keywords: convertpngs,png,gif,video,mp4,opencv,pillow,animation,convert,pngs,png2gif,png2video,png2mp4,png2avi,png2mp4,png2video
Classifier: Development Status :: 4 - Beta
Classifier: Intended Audience :: Developers
Classifier: Operating System :: OS Independent
Classifier: License :: OSI Approved :: MIT License
Classifier: Programming Language :: Python :: 3
